python_anvil_encryption/__init__.py
python_anvil_encryption/__main__.py
python_anvil_encryption/cli.py
python_anvil_encryption/encryption.py
python_anvil_encryption/py.typed
python_anvil_encryption/tests/__init__.py
python_anvil_encryption/tests/conftest.py
python_anvil_encryption/tests/data/aa.pem
python_anvil_encryption/tests/data/aa.pub
python_anvil_encryption/tests/data/aa_forge_complete_payload.json
python_anvil_encryption/tests/test_encryption.py
python_anvil_encryption-0.1.dist-info/LICENSE.md
python_anvil_encryption-0.1.dist-info/METADATA
python_anvil_encryption-0.1.dist-info/WHEEL
python_anvil_encryption-0.1.dist-info/entry_points.txt
python_anvil_encryption-0.1.dist-info/RECORD
