Metadata-Version: 2.1
Name: python-anvil-encryption
Version: 0.1
Summary: Encrypt and decrypt payloads in Anvil (https://www.useanvil.com/)
Home-page: https://pypi.org/project/python-anvil-encryption
License: MIT
Keywords: anvil,api,pdf,signing,encryption
Author: Anvil Foundry Inc.
Author-email: developers@useanvil.com
Requires-Python: >=3.7.2,<3.12
Classifier: Development Status :: 3 - Alpha
Classifier: License :: OSI Approved :: MIT License
Classifier: Natural Language :: English
Classifier: Operating System :: OS Independent
Classifier: Programming Language :: Python
Classifier: Programming Language :: Python :: 3
Classifier: Programming Language :: Python :: 3.8
Classifier: Programming Language :: Python :: 3.9
Classifier: Programming Language :: Python :: 3.10
Classifier: Programming Language :: Python :: 3.11
Classifier: Programming Language :: Python :: 3.7
Classifier: Topic :: Software Development :: Libraries :: Python Modules
Requires-Dist: click
Requires-Dist: cryptography (>=41.0.3,<42.0.0)
Requires-Dist: minilog
Project-URL: Documentation, https://python-anvil-encryption.readthedocs.io
Project-URL: Repository, https://github.com/anvilco/python-anvil-encryption
